{"OpenedDocuments":"[{\"DocumentPath\":\"invoke/invoke_02.ACME_login.xaml\",\"FactoryId\":\"{ACB8E7BA-F093-44C1-9B50-33ECA51AAE16}\"},{\"DocumentPath\":\"invoke/invoke_04.Type=WI3Status=open.xaml\",\"FactoryId\":\"{ACB8E7BA-F093-44C1-9B50-33ECA51AAE16}\"},{\"DocumentPath\":\"0_통합본.xaml\",\"FactoryId\":\"{ACB8E7BA-F093-44C1-9B50-33ECA51AAE16}\"}]","ProjectBreakpoints":"{\"CodeBreakpoints\":{},\"Value\":{}}","ProjectActivitiesViewState":"{\"0_통합본.xaml\":[{\"ActivityIdRef\":\"KillProcess_1\",\"IsAdvancedOptionsExpanded\":false,\"Widgets\":{}},{\"ActivityIdRef\":\"GetSecureCredential_1\",\"IsAdvancedOptionsExpanded\":false,\"Widgets\":{}},{\"ActivityIdRef\":\"KillProcess_2\",\"IsAdvancedOptionsExpanded\":false,\"Widgets\":{}},{\"ActivityIdRef\":\"GetPassword_2\",\"IsAdvancedOptionsExpanded\":false,\"Widgets\":{}},{\"ActivityIdRef\":\"Delay_1\",\"IsAdvancedOptionsExpanded\":false,\"Widgets\":{}},{\"ActivityIdRef\":\"MergeDataTable_1\",\"IsAdvancedOptionsExpanded\":false,\"Widgets\":{}},{\"ActivityIdRef\":\"GetPassword_1\",\"IsAdvancedOptionsExpanded\":false,\"Widgets\":{}},{\"ActivityIdRef\":\"ExcelCopySheet_2\",\"IsAdvancedOptionsExpanded\":false,\"Widgets\":{}},{\"ActivityIdRef\":\"ExcelSaveWorkbook_1\",\"IsAdvancedOptionsExpanded\":false,\"Widgets\":{}},{\"ActivityIdRef\":\"Delay_4\",\"IsAdvancedOptionsExpanded\":false,\"Widgets\":{}},{\"ActivityIdRef\":\"KillProcess_3\",\"IsAdvancedOptionsExpanded\":false,\"Widgets\":{}},{\"ActivityIdRef\":\"LookupDataTable_1\",\"IsAdvancedOptionsExpanded\":false,\"Widgets\":{}},{\"ActivityIdRef\":\"AddDataColumn`1_1\",\"IsAdvancedOptionsExpanded\":false,\"Widgets\":{}},{\"ActivityIdRef\":\"If_2\",\"IsAdvancedOptionsExpanded\":false,\"Widgets\":{\"Else\":{\"ShowExpanded\":false},\"Then\":{\"ShowExpanded\":true}}},{\"ActivityIdRef\":\"Continue_1\",\"IsAdvancedOptionsExpanded\":false,\"Widgets\":{}},{\"ActivityIdRef\":\"KillProcess_4\",\"IsAdvancedOptionsExpanded\":false,\"Widgets\":{}},{\"ActivityIdRef\":\"Delay_2\",\"IsAdvancedOptionsExpanded\":false,\"Widgets\":{}},{\"ActivityIdRef\":\"KillProcess_5\",\"IsAdvancedOptionsExpanded\":false,\"Widgets\":{}},{\"ActivityIdRef\":\"KillProcess_6\",\"IsAdvancedOptionsExpanded\":false,\"Widgets\":{}}],\"invoke/Send_Email.xaml\":[{\"ActivityIdRef\":\"If_4\",\"IsAdvancedOptionsExpanded\":false,\"Widgets\":{\"Else\":{\"ShowExpanded\":true},\"Then\":{\"ShowExpanded\":true}}}],\"invoke/UpdateWorkitem.xaml\":[{\"ActivityIdRef\":\"Delay_3\",\"IsAdvancedOptionsExpanded\":false,\"Widgets\":{}},{\"ActivityIdRef\":\"Delay_4\",\"IsAdvancedOptionsExpanded\":false,\"Widgets\":{}},{\"ActivityIdRef\":\"Delay_5\",\"IsAdvancedOptionsExpanded\":false,\"Widgets\":{}}],\"invoke/invoke_10_lookup_data_code.xaml\":[{\"ActivityIdRef\":\"AddDataColumn`1_4\",\"IsAdvancedOptionsExpanded\":false,\"Widgets\":{}},{\"ActivityIdRef\":\"AddDataColumn`1_5\",\"IsAdvancedOptionsExpanded\":false,\"Widgets\":{}},{\"ActivityIdRef\":\"AddDataColumn`1_6\",\"IsAdvancedOptionsExpanded\":false,\"Widgets\":{}},{\"ActivityIdRef\":\"LookupDataTable_5\",\"IsAdvancedOptionsExpanded\":false,\"Widgets\":{}},{\"ActivityIdRef\":\"LookupDataTable_6\",\"IsAdvancedOptionsExpanded\":false,\"Widgets\":{}},{\"ActivityIdRef\":\"LookupDataTable_7\",\"IsAdvancedOptionsExpanded\":false,\"Widgets\":{}}],\"invoke/invoke_5_PDF파일분류.xaml\":[{\"ActivityIdRef\":\"AddDataColumn`1_1\",\"IsAdvancedOptionsExpanded\":false,\"Widgets\":{}},{\"ActivityIdRef\":\"If_3\",\"IsAdvancedOptionsExpanded\":false,\"Widgets\":{\"Else\":{\"ShowExpanded\":false},\"Then\":{\"ShowExpanded\":true}}},{\"ActivityIdRef\":\"AddDataColumn`1_2\",\"IsAdvancedOptionsExpanded\":false,\"Widgets\":{}},{\"ActivityIdRef\":\"If_4\",\"IsAdvancedOptionsExpanded\":false,\"Widgets\":{\"Else\":{\"ShowExpanded\":false},\"Then\":{\"ShowExpanded\":true}}}],\"invoke/invoke_11_lookup_iso_and_main_dt.xaml\":[{\"ActivityIdRef\":\"ForEach`1_2\",\"IsAdvancedOptionsExpanded\":false,\"Categories\":{\"\":true},\"Widgets\":{\"Body\":{\"ShowExpanded\":true}}},{\"ActivityIdRef\":\"AddDataColumn`1_3\",\"IsAdvancedOptionsExpanded\":false,\"Widgets\":{}},{\"ActivityIdRef\":\"LookupDataTable_1\",\"IsAdvancedOptionsExpanded\":false,\"Widgets\":{}},{\"ActivityIdRef\":\"LookupDataTable_4\",\"IsAdvancedOptionsExpanded\":false,\"Widgets\":{}},{\"ActivityIdRef\":\"LookupDataTable_5\",\"IsAdvancedOptionsExpanded\":false,\"Widgets\":{}},{\"ActivityIdRef\":\"If_1\",\"IsAdvancedOptionsExpanded\":false,\"Widgets\":{\"Else\":{\"ShowExpanded\":false},\"Then\":{\"ShowExpanded\":true}}}],\"invoke/invoke_01.OpenBrowser.xaml\":[{\"ActivityIdRef\":\"Delay_1\",\"IsAdvancedOptionsExpanded\":false,\"Widgets\":{}}],\"invoke/ExchangeRate_Extract.xaml\":[{\"ActivityIdRef\":\"Delay_4\",\"IsAdvancedOptionsExpanded\":false,\"Widgets\":{}}],\"invoke/invoke_12-1_excel_write_1.xaml\":[{\"ActivityIdRef\":\"ExcelCopySheet_2\",\"IsAdvancedOptionsExpanded\":false,\"Widgets\":{}},{\"ActivityIdRef\":\"ExcelSaveWorkbook_1\",\"IsAdvancedOptionsExpanded\":false,\"Widgets\":{}},{\"ActivityIdRef\":\"Delay_2\",\"IsAdvancedOptionsExpanded\":false,\"Widgets\":{}}],\"invoke/invoke_12-2_excel_write_2.xaml\":[{\"ActivityIdRef\":\"AddDataColumn`1_3\",\"IsAdvancedOptionsExpanded\":false,\"Widgets\":{}},{\"ActivityIdRef\":\"AddDataColumn`1_1\",\"IsAdvancedOptionsExpanded\":false,\"Widgets\":{}},{\"ActivityIdRef\":\"AddDataColumn`1_2\",\"IsAdvancedOptionsExpanded\":false,\"Widgets\":{}},{\"ActivityIdRef\":\"ExcelInsertDeleteRows_2\",\"IsAdvancedOptionsExpanded\":false,\"Widgets\":{}},{\"ActivityIdRef\":\"ExcelSaveWorkbook_2\",\"IsAdvancedOptionsExpanded\":false,\"Widgets\":{}},{\"ActivityIdRef\":\"RemoveDuplicateRows_1\",\"IsAdvancedOptionsExpanded\":false,\"Widgets\":{}}],\"invoke/환율데이터와ISO룩업.xaml\":[{\"ActivityIdRef\":\"AddDataColumn`1_1\",\"IsAdvancedOptionsExpanded\":false,\"Widgets\":{}},{\"ActivityIdRef\":\"LookupDataTable_1\",\"IsAdvancedOptionsExpanded\":false,\"Widgets\":{}},{\"ActivityIdRef\":\"If_2\",\"IsAdvancedOptionsExpanded\":false,\"Widgets\":{\"Else\":{\"ShowExpanded\":false},\"Then\":{\"ShowExpanded\":true}}},{\"ActivityIdRef\":\"Delay_4\",\"IsAdvancedOptionsExpanded\":false,\"Widgets\":{}}],\"Main.xaml\":[{\"ActivityIdRef\":\"WriteLine_1\",\"IsAdvancedOptionsExpanded\":false,\"Widgets\":{}},{\"ActivityIdRef\":\"Delay_1\",\"IsAdvancedOptionsExpanded\":false,\"Widgets\":{}},{\"ActivityIdRef\":\"WriteLine_2\",\"IsAdvancedOptionsExpanded\":false,\"Widgets\":{}},{\"ActivityIdRef\":\"Delay_2\",\"IsAdvancedOptionsExpanded\":false,\"Widgets\":{}}],\"invoke/invoke_12-2_excel_write_2 - 복사 (1).xaml\":[{\"ActivityIdRef\":\"Continue_1\",\"IsAdvancedOptionsExpanded\":false,\"Widgets\":{}},{\"ActivityIdRef\":\"AddDataColumn`1_4\",\"IsAdvancedOptionsExpanded\":false,\"Widgets\":{}},{\"ActivityIdRef\":\"If_1\",\"IsAdvancedOptionsExpanded\":false,\"Widgets\":{\"Else\":{\"ShowExpanded\":true},\"Then\":{\"ShowExpanded\":false}}},{\"ActivityIdRef\":\"ExcelInsertDeleteRows_2\",\"IsAdvancedOptionsExpanded\":false,\"Widgets\":{}},{\"ActivityIdRef\":\"ExcelSaveWorkbook_2\",\"IsAdvancedOptionsExpanded\":false,\"Widgets\":{}}],\"invoke/invoke_05_PDF파일분류.xaml\":[{\"ActivityIdRef\":\"AddDataColumn`1_1\",\"IsAdvancedOptionsExpanded\":false,\"Widgets\":{}},{\"ActivityIdRef\":\"AddDataColumn`1_2\",\"IsAdvancedOptionsExpanded\":false,\"Widgets\":{}},{\"ActivityIdRef\":\"If_3\",\"IsAdvancedOptionsExpanded\":false,\"Widgets\":{\"Else\":{\"ShowExpanded\":false},\"Then\":{\"ShowExpanded\":true}}},{\"ActivityIdRef\":\"If_4\",\"IsAdvancedOptionsExpanded\":false,\"Widgets\":{\"Else\":{\"ShowExpanded\":false},\"Then\":{\"ShowExpanded\":true}}}],\"invoke/invoke_06-1_Type1.xaml\":[{\"ActivityIdRef\":\"ForEach`1_1\",\"IsAdvancedOptionsExpanded\":false,\"Categories\":{\"\":true},\"Widgets\":{\"Body\":{\"ShowExpanded\":true}}},{\"ActivityIdRef\":\"AddDataColumn`1_4\",\"IsAdvancedOptionsExpanded\":false,\"Widgets\":{}}],\"invoke/invoke_12-3-1_exchange_dt_make.xaml\":[{\"ActivityIdRef\":\"Delay_6\",\"IsAdvancedOptionsExpanded\":false,\"Widgets\":{}},{\"ActivityIdRef\":\"AddDataColumn`1_1\",\"IsAdvancedOptionsExpanded\":false,\"Widgets\":{}},{\"ActivityIdRef\":\"AddDataColumn`1_2\",\"IsAdvancedOptionsExpanded\":false,\"Widgets\":{}},{\"ActivityIdRef\":\"LookupDataTable_1\",\"IsAdvancedOptionsExpanded\":false,\"Widgets\":{}},{\"ActivityIdRef\":\"Delay_2\",\"IsAdvancedOptionsExpanded\":false,\"Widgets\":{}},{\"ActivityIdRef\":\"MergeDataTable_2\",\"IsAdvancedOptionsExpanded\":false,\"Widgets\":{}},{\"ActivityIdRef\":\"LookupDataTable_2\",\"IsAdvancedOptionsExpanded\":false,\"Widgets\":{}},{\"ActivityIdRef\":\"MergeDataTable_15\",\"IsAdvancedOptionsExpanded\":false,\"Widgets\":{}},{\"ActivityIdRef\":\"Delay_5\",\"IsAdvancedOptionsExpanded\":false,\"Widgets\":{}}],\"invoke/invoke_12-3-2_excel_write_3.xaml\":[{\"ActivityIdRef\":\"AddDataColumn`1_7\",\"IsAdvancedOptionsExpanded\":false,\"Widgets\":{}},{\"ActivityIdRef\":\"LookupDataTable_1\",\"IsAdvancedOptionsExpanded\":false,\"Widgets\":{}},{\"ActivityIdRef\":\"AddDataColumn`1_4\",\"IsAdvancedOptionsExpanded\":false,\"Widgets\":{}},{\"ActivityIdRef\":\"If_1\",\"IsAdvancedOptionsExpanded\":false,\"Widgets\":{\"Else\":{\"ShowExpanded\":false},\"Then\":{\"ShowExpanded\":true}}},{\"ActivityIdRef\":\"Continue_1\",\"IsAdvancedOptionsExpanded\":false,\"Widgets\":{}}],\"invoke/invoke_07_vendor_search_이동및조사.xaml\":[{\"ActivityIdRef\":\"AddDataColumn`1_1\",\"IsAdvancedOptionsExpanded\":false,\"Widgets\":{}},{\"ActivityIdRef\":\"Delay_1\",\"IsAdvancedOptionsExpanded\":false,\"Widgets\":{}},{\"ActivityIdRef\":\"If_1\",\"IsAdvancedOptionsExpanded\":false,\"Widgets\":{\"Else\":{\"ShowExpanded\":false},\"Then\":{\"ShowExpanded\":true}}}],\"invoke/invoke_09_Add_invoice_Detail_입력.xaml\":[{\"ActivityIdRef\":\"Delay_2\",\"IsAdvancedOptionsExpanded\":false,\"Widgets\":{}}],\"invoke/invoke_08-1_UpdateWorkitem.xaml\":[{\"ActivityIdRef\":\"Delay_10\",\"IsAdvancedOptionsExpanded\":false,\"Widgets\":{}}],\"invoke/invoke_13-1_Send_Email_NoExist_2.xaml\":[{\"ActivityIdRef\":\"If_4\",\"IsAdvancedOptionsExpanded\":false,\"Widgets\":{\"Else\":{\"ShowExpanded\":true},\"Then\":{\"ShowExpanded\":true}}}],\"invoke/invoke_13-2_Send_Email_NoExist_1.xaml\":[{\"ActivityIdRef\":\"If_1\",\"IsAdvancedOptionsExpanded\":false,\"Widgets\":{\"Else\":{\"ShowExpanded\":true},\"Then\":{\"ShowExpanded\":true}}}],\"invoke/invoke_02.ACME_login.xaml\":[],\"invoke/invoke_04.Type=WI3Status=open.xaml\":[{\"ActivityIdRef\":\"Delay_2\",\"IsAdvancedOptionsExpanded\":false,\"Widgets\":{}},{\"ActivityIdRef\":\"Delay_1\",\"IsAdvancedOptionsExpanded\":false,\"Widgets\":{}}]}","Compiler":"2","ProjectWatches":"{\"Value\":[]}"}